LICENSE
MANIFEST.in
README.md
setup.py
django_info/__init__.py
django_info/__init__.pyc
django_info/urls.py
django_info/views.py
django_info.egg-info/PKG-INFO
django_info.egg-info/SOURCES.txt
django_info.egg-info/dependency_links.txt
django_info.egg-info/requires.txt
django_info.egg-info/top_level.txt
django_info/templates/info.html