Metadata-Version: 1.1
Name: django-info
Version: 0.0.3
Summary: Django application to display useful information about a Django project.
Home-page: https://github.com/marcelor/django_info
Author: marcelor
Author-email: marcelor@gmail.com
License: BSD
Download-URL: https://github.com/marcelor/django_info/zipball/master/
Keywords: django,runtime information,installed apps
Platform: UNKNOWN
Classifier: Framework :: Django
Classifier: Development Status :: 3 - Alpha
Classifier: Topic :: Internet
Classifier: License :: OSI Approved :: BSD License
Classifier: Intended Audience :: Developers
Classifier: Environment :: Web Environment
Classifier: Programming Language :: Python :: 2.5
Classifier: Programming Language :: Python :: 2.6
Classifier: Programming Language :: Python :: 2.7
